{"cameraMode":{"drawMode":0,"name":"Shaded","section":"Shading Mode"},"sceneLighting":true,"audioPlay":false,"sceneViewState":{"showFog":true,"showMaterialUpdate":false,"showSkybox":true,"showFlares":true,"showImageEffects":true,"showParticleSystems":true},"in2DMode":false,"pivot":{"x":37.3765869140625,"y":-23.175357818603517,"z":-77.73646545410156},"rotation":{"x":-0.02460751309990883,"y":0.9699430465698242,"z":-0.21526196599006654,"w":-0.11075770854949951},"size":72.58733367919922,"orthographic":false}